{"FixedFileInfo":{"FileVersion":{"Major":1,"Minor":0,"Patch":0,"Build":0},"ProductVersion":{"Major":1,"Minor":0,"Patch":0,"Build":0},"FileFlagsMask":"3f","FileFlags":"","FileOS":"040004","FileType":"01","FileSubType":"00"},"StringFileInfo":{"Comments":"","CompanyName":"","FileDescription":"","FileVersion":"","InternalName":"","LegalCopyright":"","LegalTrademarks":"","OriginalFilename":"","PrivateBuild":"","ProductName":"","ProductVersion":"v1.0.0.0","SpecialBuild":""},"VarFileInfo":{"Translation":{"LangID":1033,"CharsetID":1200}},"Timestamp":false,"Buffer":{},"Structure":{"WLength":0,"WValueLength":0,"WType":0,"SzKey":null,"Padding1":null,"Value":{"DwSignature":0,"DwStrucVersion":0,"DwFileVersionMS":0,"DwFileVersionLS":0,"DwProductVersionMS":0,"DwProductVersionLS":0,"DwFileFlagsMask":0,"DwFileFlags":0,"DwFileOS":0,"DwFileType":0,"DwFileSubtype":0,"DwFileDateMS":0,"DwFileDateLS":0},"Padding2":null,"Children":{"WLength":0,"WValueLength":0,"WType":0,"SzKey":null,"Padding":null,"Children":{"WLength":0,"WValueLength":0,"WType":0,"SzKey":null,"Padding":null,"Children":null}},"Children2":{"WLength":0,"WValueLength":0,"WType":0,"SzKey":null,"Padding":null,"Value":{"WLength":0,"WValueLength":0,"WType":0,"SzKey":null,"Padding":null,"Value":0}}},"IconPath":"","ManifestPath":""}